MANIFEST.in
README.md
setup.py
linh/__init__.py
linh/models.py
linh/tests.py
linh.egg-info/PKG-INFO
linh.egg-info/SOURCES.txt
linh.egg-info/dependency_links.txt
linh.egg-info/not-zip-safe
linh.egg-info/requires.txt
linh.egg-info/top_level.txt