Metadata-Version: 1.0
Name: linh
Version: 0.0.1
Summary: Linh is not HTML
Home-page: http://pypi.python.org/pypi/linh/
Author: André Farzat
Author-email: andrefarzat@gmail.com
License: LICENSE
Platform: UNKNOWN
